pyanide/__init__.py
pyanide/__main__.py
pyanide/main.py
pyanide/py.typed
pyanide-1.1.0.dist-info/LICENSE
pyanide-1.1.0.dist-info/METADATA
pyanide-1.1.0.dist-info/WHEEL
pyanide-1.1.0.dist-info/RECORD
